attr_dict/__init__.py
attr_dict/attrdict.py
attr_dict/index.py
Attr_Dict-1.0.0.dist-info/LICENSE
Attr_Dict-1.0.0.dist-info/METADATA
Attr_Dict-1.0.0.dist-info/WHEEL
Attr_Dict-1.0.0.dist-info/top_level.txt
Attr_Dict-1.0.0.dist-info/zip-safe
Attr_Dict-1.0.0.dist-info/RECORD
