Metadata-Version: 2.1
Name: Attr-Dict
Version: 1.0.0
Summary: Yet another Attribute Dict implementation !
Home-page: https://github.com/LuckyDams/Attr-Dict
Author: LuckyDams
Author-email: LuckyDams@gmail.org
License: MIT
Platform: any
Classifier: Development Status :: 4 - Beta
Classifier: Programming Language :: Python :: 3
Classifier: License :: OSI Approved :: MIT License
Classifier: Operating System :: OS Independent
Classifier: Intended Audience :: Developers
Classifier: Topic :: Software Development :: Libraries :: Python Modules
Classifier: Topic :: Utilities
